{
  "annotations": {
    "list": [
      {
        "builtIn": 1,
        "datasource": {
          "type": "grafana",
          "uid": "-- Grafana --"
        },
        "enable": true,
        "hide": true,
        "iconColor": "rgba(0, 211, 255, 1)",
        "name": "Annotations & Alerts",
        "type": "dashboard"
      }
    ]
  },
  "editable": false,
  "fiscalYearStartMonth": 0,
  "graphTooltip": 1,
  "id": null,
  "links": [
    {
      "asDropdown": false,
      "icon": "external link",
      "includeVars": true,
      "keepTime": true,
      "targetBlank": false,
      "title": "VictoriaMetrics Explore",
      "type": "link",
      "url": "/explore?left={\"datasource\":\"victoriametrics\",\"queries\":[{\"expr\":\"homeassistant_sensor_power_w\"}],\"range\":{\"from\":\"now-24h\",\"to\":\"now\"}}"
    }
  ],
  "panels": [
    {
      "id": 1,
      "type": "stat",
      "title": "Home Assistant scrape",
      "gridPos": {
        "x": 0,
        "y": 0,
        "w": 6,
        "h": 4
      },
      "datasource": {
        "type": "prometheus",
        "uid": "victoriametrics"
      },
      "targets": [
        {
          "refId": "A",
          "expr": "up{job=\"homeassistant\"}",
          "legendFormat": "HA",
          "datasource": {
            "type": "prometheus",
            "uid": "victoriametrics"
          }
        }
      ],
      "fieldConfig": {
        "defaults": {
          "unit": "bool_on_off",
          "thresholds": {
            "mode": "absolute",
            "steps": [
              {
                "color": "green",
                "value": null
              }
            ]
          }
        },
        "overrides": []
      },
      "options": {
        "reduceOptions": {
          "values": false,
          "calcs": [
            "lastNotNull"
          ],
          "fields": ""
        },
        "orientation": "auto",
        "textMode": "auto",
        "wideLayout": true,
        "colorMode": "background",
        "graphMode": "area",
        "justifyMode": "auto",
        "showPercentChange": false
      },
      "description": "Prometheus scrape health for Home Assistant exporter."
    },
    {
      "id": 2,
      "type": "stat",
      "title": "Total live plug load",
      "gridPos": {
        "x": 6,
        "y": 0,
        "w": 6,
        "h": 4
      },
      "datasource": {
        "type": "prometheus",
        "uid": "victoriametrics"
      },
      "targets": [
        {
          "refId": "A",
          "expr": "sum(homeassistant_sensor_power_w{entity=\"sensor.main_power_power\"} or homeassistant_sensor_power_w{entity=\"sensor.kettle_co_sonoff_1002700ec0_power\"})",
          "legendFormat": "Total",
          "datasource": {
            "type": "prometheus",
            "uid": "victoriametrics"
          }
        }
      ],
      "fieldConfig": {
        "defaults": {
          "unit": "watt",
          "thresholds": {
            "mode": "absolute",
            "steps": [
              {
                "color": "green",
                "value": null
              }
            ]
          }
        },
        "overrides": []
      },
      "options": {
        "reduceOptions": {
          "values": false,
          "calcs": [
            "lastNotNull"
          ],
          "fields": ""
        },
        "orientation": "auto",
        "textMode": "auto",
        "wideLayout": true,
        "colorMode": "background",
        "graphMode": "area",
        "justifyMode": "auto",
        "showPercentChange": false
      },
      "description": "Sum of live wattage from Main_power and Kettle_Co smart plugs."
    },
    {
      "id": 3,
      "type": "stat",
      "title": "Main_power cumulative energy",
      "gridPos": {
        "x": 12,
        "y": 0,
        "w": 6,
        "h": 4
      },
      "datasource": {
        "type": "prometheus",
        "uid": "victoriametrics"
      },
      "targets": [
        {
          "refId": "A",
          "expr": "homeassistant_sensor_energy_wh{entity=\"sensor.main_power_energy\"} / 1000",
          "legendFormat": "Main_power",
          "datasource": {
            "type": "prometheus",
            "uid": "victoriametrics"
          }
        }
      ],
      "fieldConfig": {
        "defaults": {
          "unit": "kwatth",
          "thresholds": {
            "mode": "absolute",
            "steps": [
              {
                "color": "green",
                "value": null
              }
            ]
          }
        },
        "overrides": []
      },
      "options": {
        "reduceOptions": {
          "values": false,
          "calcs": [
            "lastNotNull"
          ],
          "fields": ""
        },
        "orientation": "auto",
        "textMode": "auto",
        "wideLayout": true,
        "colorMode": "background",
        "graphMode": "area",
        "justifyMode": "auto",
        "showPercentChange": false
      },
      "description": "Meross Main_power energy converted from Wh to kWh."
    },
    {
      "id": 4,
      "type": "stat",
      "title": "Kettle day energy",
      "gridPos": {
        "x": 18,
        "y": 0,
        "w": 6,
        "h": 4
      },
      "datasource": {
        "type": "prometheus",
        "uid": "victoriametrics"
      },
      "targets": [
        {
          "refId": "A",
          "expr": "homeassistant_sensor_energy_kwh{entity=\"sensor.kettle_co_sonoff_1002700ec0_energy_day\"}",
          "legendFormat": "Kettle_Co day",
          "datasource": {
            "type": "prometheus",
            "uid": "victoriametrics"
          }
        }
      ],
      "fieldConfig": {
        "defaults": {
          "unit": "kwatth",
          "thresholds": {
            "mode": "absolute",
            "steps": [
              {
                "color": "green",
                "value": null
              }
            ]
          }
        },
        "overrides": []
      },
      "options": {
        "reduceOptions": {
          "values": false,
          "calcs": [
            "lastNotNull"
          ],
          "fields": ""
        },
        "orientation": "auto",
        "textMode": "auto",
        "wideLayout": true,
        "colorMode": "background",
        "graphMode": "area",
        "justifyMode": "auto",
        "showPercentChange": false
      },
      "description": "Sonoff kettle daily energy counter."
    },
    {
      "id": 5,
      "type": "timeseries",
      "title": "Live power",
      "gridPos": {
        "x": 0,
        "y": 4,
        "w": 24,
        "h": 8
      },
      "datasource": {
        "type": "prometheus",
        "uid": "victoriametrics"
      },
      "targets": [
        {
          "refId": "A",
          "expr": "homeassistant_sensor_power_w{entity=\"sensor.main_power_power\"} or homeassistant_sensor_power_w{entity=\"sensor.kettle_co_sonoff_1002700ec0_power\"}",
          "legendFormat": "{{friendly_name}}",
          "datasource": {
            "type": "prometheus",
            "uid": "victoriametrics"
          }
        }
      ],
      "fieldConfig": {
        "defaults": {
          "unit": "watt",
          "custom": {
            "drawStyle": "line",
            "lineInterpolation": "linear",
            "barAlignment": 0,
            "lineWidth": 1,
            "fillOpacity": 12,
            "gradientMode": "none",
            "spanNulls": false,
            "insertNulls": false,
            "showPoints": "never",
            "pointSize": 5,
            "stacking": {
              "mode": "none",
              "group": "A"
            },
            "axisPlacement": "auto",
            "axisLabel": "",
            "axisColorMode": "text",
            "axisBorderShow": false,
            "scaleDistribution": {
              "type": "linear"
            },
            "axisCenteredZero": false,
            "hideFrom": {
              "tooltip": false,
              "viz": false,
              "legend": false
            },
            "thresholdsStyle": {
              "mode": "off"
            }
          },
          "thresholds": {
            "mode": "absolute",
            "steps": [
              {
                "color": "green",
                "value": null
              }
            ]
          }
        },
        "overrides": []
      },
      "options": {
        "tooltip": {
          "mode": "multi",
          "sort": "none"
        },
        "legend": {
          "showLegend": true,
          "displayMode": "list",
          "placement": "bottom",
          "calcs": [
            "lastNotNull"
          ]
        }
      },
      "description": "Live power draw per smart plug."
    },
    {
      "id": 6,
      "type": "timeseries",
      "title": "Energy counters",
      "gridPos": {
        "x": 0,
        "y": 12,
        "w": 12,
        "h": 8
      },
      "datasource": {
        "type": "prometheus",
        "uid": "victoriametrics"
      },
      "targets": [
        {
          "refId": "A",
          "expr": "(homeassistant_sensor_energy_wh{entity=\"sensor.main_power_energy\"} / 1000) or homeassistant_sensor_energy_kwh{entity=\"sensor.kettle_co_sonoff_1002700ec0_energy_day\"} or homeassistant_sensor_energy_kwh{entity=\"sensor.kettle_co_sonoff_1002700ec0_energy_month\"}",
          "legendFormat": "{{friendly_name}}",
          "datasource": {
            "type": "prometheus",
            "uid": "victoriametrics"
          }
        }
      ],
      "fieldConfig": {
        "defaults": {
          "unit": "kwatth",
          "custom": {
            "drawStyle": "line",
            "lineInterpolation": "linear",
            "barAlignment": 0,
            "lineWidth": 1,
            "fillOpacity": 12,
            "gradientMode": "none",
            "spanNulls": false,
            "insertNulls": false,
            "showPoints": "never",
            "pointSize": 5,
            "stacking": {
              "mode": "none",
              "group": "A"
            },
            "axisPlacement": "auto",
            "axisLabel": "",
            "axisColorMode": "text",
            "axisBorderShow": false,
            "scaleDistribution": {
              "type": "linear"
            },
            "axisCenteredZero": false,
            "hideFrom": {
              "tooltip": false,
              "viz": false,
              "legend": false
            },
            "thresholdsStyle": {
              "mode": "off"
            }
          },
          "thresholds": {
            "mode": "absolute",
            "steps": [
              {
                "color": "green",
                "value": null
              }
            ]
          }
        },
        "overrides": []
      },
      "options": {
        "tooltip": {
          "mode": "multi",
          "sort": "none"
        },
        "legend": {
          "showLegend": true,
          "displayMode": "list",
          "placement": "bottom",
          "calcs": [
            "lastNotNull"
          ]
        }
      },
      "description": "Energy counters. Main_power is Wh converted to kWh; Kettle_Co exposes day/month kWh counters."
    },
    {
      "id": 7,
      "type": "timeseries",
      "title": "Current",
      "gridPos": {
        "x": 12,
        "y": 12,
        "w": 6,
        "h": 8
      },
      "datasource": {
        "type": "prometheus",
        "uid": "victoriametrics"
      },
      "targets": [
        {
          "refId": "A",
          "expr": "homeassistant_sensor_current_a{entity=\"sensor.main_power_current\"} or homeassistant_sensor_current_a{entity=\"sensor.kettle_co_sonoff_1002700ec0_current\"}",
          "legendFormat": "{{friendly_name}}",
          "datasource": {
            "type": "prometheus",
            "uid": "victoriametrics"
          }
        }
      ],
      "fieldConfig": {
        "defaults": {
          "unit": "amp",
          "custom": {
            "drawStyle": "line",
            "lineInterpolation": "linear",
            "barAlignment": 0,
            "lineWidth": 1,
            "fillOpacity": 12,
            "gradientMode": "none",
            "spanNulls": false,
            "insertNulls": false,
            "showPoints": "never",
            "pointSize": 5,
            "stacking": {
              "mode": "none",
              "group": "A"
            },
            "axisPlacement": "auto",
            "axisLabel": "",
            "axisColorMode": "text",
            "axisBorderShow": false,
            "scaleDistribution": {
              "type": "linear"
            },
            "axisCenteredZero": false,
            "hideFrom": {
              "tooltip": false,
              "viz": false,
              "legend": false
            },
            "thresholdsStyle": {
              "mode": "off"
            }
          },
          "thresholds": {
            "mode": "absolute",
            "steps": [
              {
                "color": "green",
                "value": null
              }
            ]
          }
        },
        "overrides": []
      },
      "options": {
        "tooltip": {
          "mode": "multi",
          "sort": "none"
        },
        "legend": {
          "showLegend": true,
          "displayMode": "list",
          "placement": "bottom",
          "calcs": [
            "lastNotNull"
          ]
        }
      },
      "description": "Current draw per plug."
    },
    {
      "id": 8,
      "type": "timeseries",
      "title": "Voltage",
      "gridPos": {
        "x": 18,
        "y": 12,
        "w": 6,
        "h": 8
      },
      "datasource": {
        "type": "prometheus",
        "uid": "victoriametrics"
      },
      "targets": [
        {
          "refId": "A",
          "expr": "homeassistant_sensor_voltage_v{entity=\"sensor.main_power_voltage\"} or homeassistant_sensor_voltage_v{entity=\"sensor.kettle_co_sonoff_1002700ec0_voltage\"}",
          "legendFormat": "{{friendly_name}}",
          "datasource": {
            "type": "prometheus",
            "uid": "victoriametrics"
          }
        }
      ],
      "fieldConfig": {
        "defaults": {
          "unit": "volt",
          "custom": {
            "drawStyle": "line",
            "lineInterpolation": "linear",
            "barAlignment": 0,
            "lineWidth": 1,
            "fillOpacity": 12,
            "gradientMode": "none",
            "spanNulls": false,
            "insertNulls": false,
            "showPoints": "never",
            "pointSize": 5,
            "stacking": {
              "mode": "none",
              "group": "A"
            },
            "axisPlacement": "auto",
            "axisLabel": "",
            "axisColorMode": "text",
            "axisBorderShow": false,
            "scaleDistribution": {
              "type": "linear"
            },
            "axisCenteredZero": false,
            "hideFrom": {
              "tooltip": false,
              "viz": false,
              "legend": false
            },
            "thresholdsStyle": {
              "mode": "off"
            }
          },
          "thresholds": {
            "mode": "absolute",
            "steps": [
              {
                "color": "green",
                "value": null
              }
            ]
          }
        },
        "overrides": []
      },
      "options": {
        "tooltip": {
          "mode": "multi",
          "sort": "none"
        },
        "legend": {
          "showLegend": true,
          "displayMode": "list",
          "placement": "bottom",
          "calcs": [
            "lastNotNull"
          ]
        }
      },
      "description": "Reported mains voltage per plug."
    },
    {
      "id": 9,
      "type": "timeseries",
      "title": "Switch states",
      "gridPos": {
        "x": 0,
        "y": 20,
        "w": 24,
        "h": 6
      },
      "datasource": {
        "type": "prometheus",
        "uid": "victoriametrics"
      },
      "targets": [
        {
          "refId": "A",
          "expr": "homeassistant_switch_state{entity=\"switch.main_power_outlet\"} or homeassistant_switch_state{entity=\"switch.kettle_co_sonoff_1002700ec0_1\"} or homeassistant_switch_state{entity=\"switch.power_strip_outlet\"} or homeassistant_switch_state{entity=\"switch.power_strip_outlet_1\"} or homeassistant_switch_state{entity=\"switch.power_strip_outlet_2\"} or homeassistant_switch_state{entity=\"switch.power_strip_outlet_3\"} or homeassistant_switch_state{entity=\"switch.power_strip_outlet_4\"}",
          "legendFormat": "{{friendly_name}}",
          "datasource": {
            "type": "prometheus",
            "uid": "victoriametrics"
          }
        }
      ],
      "fieldConfig": {
        "defaults": {
          "unit": "bool_on_off",
          "custom": {
            "drawStyle": "line",
            "lineInterpolation": "linear",
            "barAlignment": 0,
            "lineWidth": 1,
            "fillOpacity": 12,
            "gradientMode": "none",
            "spanNulls": false,
            "insertNulls": false,
            "showPoints": "never",
            "pointSize": 5,
            "stacking": {
              "mode": "none",
              "group": "A"
            },
            "axisPlacement": "auto",
            "axisLabel": "",
            "axisColorMode": "text",
            "axisBorderShow": false,
            "scaleDistribution": {
              "type": "linear"
            },
            "axisCenteredZero": false,
            "hideFrom": {
              "tooltip": false,
              "viz": false,
              "legend": false
            },
            "thresholdsStyle": {
              "mode": "off"
            }
          },
          "thresholds": {
            "mode": "absolute",
            "steps": [
              {
                "color": "green",
                "value": null
              }
            ]
          }
        },
        "overrides": []
      },
      "options": {
        "tooltip": {
          "mode": "multi",
          "sort": "none"
        },
        "legend": {
          "showLegend": true,
          "displayMode": "list",
          "placement": "bottom",
          "calcs": [
            "lastNotNull"
          ]
        }
      },
      "description": "Switch state for smart plug outlets, where 1 is on and 0 is off."
    }
  ],
  "refresh": "30s",
  "schemaVersion": 41,
  "tags": [
    "home-network",
    "energy",
    "home-assistant",
    "victoriametrics"
  ],
  "templating": {
    "list": []
  },
  "time": {
    "from": "now-24h",
    "to": "now"
  },
  "timepicker": {},
  "timezone": "browser",
  "title": "Energy Overview",
  "uid": "energy-overview",
  "version": 1,
  "weekStart": ""
}
